{
    "+traits": [
        "legacyLaunch",
        "texturepacks"
    ],
    "assetIndex": {
        "id": "legacy",
        "sha1": "c0fd82e8ce9fbc93119e40d96d5a4e62cfa3f729",
        "size": 134284,
        "totalSize": 111220701,
        "url": "https://launchermeta.mojang.com/mc/assets/legacy/c0fd82e8ce9fbc93119e40d96d5a4e62cfa3f729/legacy.json"
    },
    "downloads": {
        "client": {
            "sha1": "3139e9c29b2c74f59ea04de760ac2af5bc21b410",
            "size": 1994742,
            "url": "https://launcher.mojang.com/mc/game/b1.8/client/3139e9c29b2c74f59ea04de760ac2af5bc21b410/client.jar"
        }
    },
    "formatVersion": 0,
    "name": "Minecraft",
    "releaseTime": "2011-09-15T00:00:00+02:00",
    "type": "old_beta",
    "uid": "net.minecraft",
    "version": "b1.8"
}