{
    "formatVersion": 0,
    "name": "Minecraft",
    "uid": "net.minecraft",
    "versions": [
        {
            "releaseTime": "2017-04-05T13:58:01+00:00",
            "requires": {
                "org.lwjgl": "2.*"
            },
            "sha256": "4e8d311517e7a1b12de11cc18a77218b785f45c3805dce3a65392c60dd22bcd2",
            "type": "snapshot",
            "version": "17w14a"
        },
        {
            "releaseTime": "2017-03-31T11:06:35+00:00",
            "requires": {
                "org.lwjgl": "2.*"
            },
            "sha256": "5d47522a916c072f76f43fe4b3e5eaba1b4ed95fbf09e4ae272d68ee97df33fb",
            "type": "snapshot",
            "version": "17w13b"
        },
        {
            "releaseTime": "2017-02-08T13:16:29+00:00",
            "requires": {
                "org.lwjgl": "2.*"
            },
            "sha256": "e7fe58623d458041fbb7df5eedb4119e1373793b252940b20a0843ee4b796566",
            "type": "snapshot",
            "version": "17w06a"
        },
        {
            "recommended": true,
            "releaseTime": "2016-12-21T09:29:12+00:00",
            "requires": {
                "org.lwjgl": "2.*"
            },
            "sha256": "600cf126729c89493b3c3fde0bcf8bf2281a9066da6272658f9f0d571aaf0bc9",
            "type": "release",
            "version": "1.11.2"
        },
        {
            "releaseTime": "2016-12-20T14:05:34+00:00",
            "requires": {
                "org.lwjgl": "2.*"
            },
            "sha256": "40e99706a6f89f75402b969d135f905f03cd7263cab0be69b24dfc2ad62f77c3",
            "type": "release",
            "version": "1.11.1"
        },
        {
            "releaseTime": "2016-12-15T14:38:52+00:00",
            "requires": {
                "org.lwjgl": "2.*"
            },
            "sha256": "f3631fd5cebc751cc67d430ebb23232b4306e74d352f030bf46b411bc554f740",
            "type": "snapshot",
            "version": "16w50a"
        },
        {
            "releaseTime": "2016-11-14T14:34:40+00:00",
            "requires": {
                "org.lwjgl": "2.*"
            },
            "sha256": "8fc0149c14acf9e168697970959227a317ee70e850ad6b65136c5e71972e8f06",
            "type": "release",
            "version": "1.11"
        },
        {
            "releaseTime": "2016-11-03T14:17:11+00:00",
            "requires": {
                "org.lwjgl": "2.*"
            },
            "sha256": "521f6e9aaf1c0fde2cbc38559773c2437dba61de5bae8c2027835eb2d81f4ae4",
            "type": "snapshot",
            "version": "16w44a"
        },
        {
            "releaseTime": "2016-10-27T09:00:51+00:00",
            "requires": {
                "org.lwjgl": "2.*"
            },
            "sha256": "8a59c750bdff17b59cd93c8d7ab13588f485a74b5e1662ad5e40ac0e9a011dca",
            "type": "snapshot",
            "version": "16w43a"
        },
        {
            "releaseTime": "2016-10-19T11:17:47+00:00",
            "requires": {
                "org.lwjgl": "2.*"
            },
            "sha256": "b06b4e04cf8e81d9456c5a7bd9266f5557d53e5d73518e364e05c156c82e3ab8",
            "type": "snapshot",
            "version": "16w42a"
        },
        {
            "releaseTime": "2016-10-13T14:28:35+00:00",
            "requires": {
                "org.lwjgl": "2.*"
            },
            "sha256": "f5f78c141509ad9249ec4a2611744526aa20665791d3a3ca81b439546dd9080e",
            "type": "snapshot",
            "version": "16w41a"
        },
        {
            "releaseTime": "2016-10-06T13:57:59+00:00",
            "requires": {
                "org.lwjgl": "2.*"
            },
            "sha256": "2de0c0dbf1de9dcc08a31f3bc8b5c8301e3737cc5928bc82e63332ec1f1ab8a6",
            "type": "snapshot",
            "version": "16w40a"
        },
        {
            "releaseTime": "2016-09-30T14:11:48+00:00",
            "requires": {
                "org.lwjgl": "2.*"
            },
            "sha256": "fc99e521233ba14e4b67c1a005a2aa40883916152d5fd1de3250a0bdb5a31ea4",
            "type": "snapshot",
            "version": "16w39c"
        },
        {
            "releaseTime": "2016-09-20T12:40:49+00:00",
            "requires": {
                "org.lwjgl": "2.*"
            },
            "sha256": "89847d0a6effb88575413905513c5ad68d11e917202ce1de6550923e7d856c2c",
            "type": "snapshot",
            "version": "16w38a"
        },
        {
            "releaseTime": "2016-09-08T14:55:10+00:00",
            "requires": {
                "org.lwjgl": "2.*"
            },
            "sha256": "45fb929f889b035527943d727e997ca001fb2e181f5ce0eae85b1e1397d55fcf",
            "type": "snapshot",
            "version": "16w36a"
        },
        {
            "releaseTime": "2016-09-01T13:13:38+00:00",
            "requires": {
                "org.lwjgl": "2.*"
            },
            "sha256": "4cc3cc07d32ce7790de0c1ae8172fd0321932e734485e3cbc797c43f3997bb64",
            "type": "snapshot",
            "version": "16w35a"
        },
        {
            "releaseTime": "2016-06-23T09:17:32+00:00",
            "requires": {
                "org.lwjgl": "2.*"
            },
            "sha256": "79148fb5f6299b7a7b8941129057ebbcb4caf8612f1e768051d57fd026338d77",
            "type": "release",
            "version": "1.10.2"
        },
        {
            "releaseTime": "2016-06-22T10:13:22+00:00",
            "requires": {
                "org.lwjgl": "2.*"
            },
            "sha256": "d5cf9fe34b6ee7c5a665c77561023dafe6f34514f31ff534b90409982adfaf07",
            "type": "release",
            "version": "1.10.1"
        },
        {
            "releaseTime": "2016-06-08T13:06:18+00:00",
            "requires": {
                "org.lwjgl": "2.*"
            },
            "sha256": "14b3fb68bebe17e9fae83fc263d87e2c5250eed770be8dfa9280ca4955bc6052",
            "type": "release",
            "version": "1.10"
        },
        {
            "releaseTime": "2016-05-10T10:17:16+00:00",
            "requires": {
                "org.lwjgl": "2.*"
            },
            "sha256": "83cdd0a9c70e56d15b449f1914f0dabe763e7dd5ffd640207e415d42f3b4e5c0",
            "type": "release",
            "version": "1.9.4"
        },
        {
            "releaseTime": "2016-05-10T08:33:35+00:00",
            "requires": {
                "org.lwjgl": "2.*"
            },
            "sha256": "4ab144c7a8ca5cb6d0fc6df95cf199ed2c2156c22c6d714a34c6b004186c87eb",
            "type": "release",
            "version": "1.9.3"
        },
        {
            "releaseTime": "2016-03-30T15:23:55+00:00",
            "requires": {
                "org.lwjgl": "2.*"
            },
            "sha256": "616295f9007b557c5e9393ac7772659efe01549f4d70877cf840621a0ec9b8eb",
            "type": "release",
            "version": "1.9.2"
        },
        {
            "releaseTime": "2016-03-30T13:43:07+00:00",
            "requires": {
                "org.lwjgl": "2.*"
            },
            "sha256": "596fc0f4e2d566388f9da04ef0bd288e614b6475f51a1b6591d96a74a0faab17",
            "type": "release",
            "version": "1.9.1"
        },
        {
            "releaseTime": "2016-02-29T13:49:54+00:00",
            "requires": {
                "org.lwjgl": "2.*"
            },
            "sha256": "131aae29f1497b421320fa8cdaf2a0177d8cc51174f736c8d51bc9db4a5a4c1b",
            "type": "release",
            "version": "1.9"
        },
        {
            "releaseTime": "2015-12-03T09:24:39+00:00",
            "requires": {
                "org.lwjgl": "2.*"
            },
            "sha256": "972a680264be4300b6bfa4852361b83d6181f44a82e603590d848853c27e3eed",
            "type": "release",
            "version": "1.8.9"
        },
        {
            "releaseTime": "2015-07-27T10:31:28+00:00",
            "requires": {
                "org.lwjgl": "2.*"
            },
            "sha256": "42d0bc33845685555ab167a9cce01a10731c9ae8fb5fc103d5273c76649b28ab",
            "type": "release",
            "version": "1.8.8"
        },
        {
            "releaseTime": "2015-06-05T10:10:44+00:00",
            "requires": {
                "org.lwjgl": "2.*"
            },
            "sha256": "701101d6afa6cc439882b75ac0ff99b243d967ba55f77968a14243c47ef7c0f1",
            "type": "release",
            "version": "1.8.7"
        },
        {
            "releaseTime": "2015-05-25T10:31:19+00:00",
            "requires": {
                "org.lwjgl": "2.*"
            },
            "sha256": "b1fda61646594e1cbe07417b69cf8c9b28a48eb7751e613f507ae0aed2ff13fa",
            "type": "release",
            "version": "1.8.6"
        },
        {
            "releaseTime": "2015-05-22T11:15:28+00:00",
            "requires": {
                "org.lwjgl": "2.*"
            },
            "sha256": "7725e25f7b8a2402bcba2ff63ee3aa96245b2caf36a993358a4be386381796ff",
            "type": "release",
            "version": "1.8.5"
        },
        {
            "releaseTime": "2015-04-17T11:37:50+00:00",
            "requires": {
                "org.lwjgl": "2.*"
            },
            "sha256": "57d1e5cdf9f981e9bfb5507bc34e9e6e74a49a20dd6788b3358415e571d1d6c3",
            "type": "release",
            "version": "1.8.4"
        },
        {
            "releaseTime": "2015-02-20T14:00:09+00:00",
            "requires": {
                "org.lwjgl": "2.*"
            },
            "sha256": "31bafe4d5cc489783cffc244ec45b961113482ab97f526141fb12a11c7f4f810",
            "type": "release",
            "version": "1.8.3"
        },
        {
            "releaseTime": "2015-02-19T15:47:29+00:00",
            "requires": {
                "org.lwjgl": "2.*"
            },
            "sha256": "a80da0329e2b50b1becec97c2d18b5bbcc7c93fe5494dc5908a07ade094d7872",
            "type": "release",
            "version": "1.8.2"
        },
        {
            "releaseTime": "2014-11-24T14:13:31+00:00",
            "requires": {
                "org.lwjgl": "2.*"
            },
            "sha256": "d731c4f86195a436e119b550d28837cdf718db6a05f8f9947b8393acc3b46107",
            "type": "release",
            "version": "1.8.1"
        },
        {
            "releaseTime": "2014-09-02T08:24:35+00:00",
            "requires": {
                "org.lwjgl": "2.*"
            },
            "sha256": "fbfb2b72631cdf7309190c0eaf7d6b9e70b924cff83aae86da54f79494758af1",
            "type": "release",
            "version": "1.8"
        },
        {
            "releaseTime": "2014-05-14T17:29:23+00:00",
            "requires": {
                "org.lwjgl": "2.*"
            },
            "sha256": "385a5b390dcbc08713a12690c3e268a1435b6466bb6d0b43f4003df46e267654",
            "type": "release",
            "version": "1.7.10"
        },
        {
            "releaseTime": "2014-04-14T13:29:23+00:00",
            "requires": {
                "org.lwjgl": "2.*"
            },
            "sha256": "dee33d84c420532e37929a65bf724f908dae9f329de0f618e0a7925f7eef9a5b",
            "type": "release",
            "version": "1.7.9"
        },
        {
            "releaseTime": "2014-04-09T07:58:16+00:00",
            "requires": {
                "org.lwjgl": "2.*"
            },
            "sha256": "65d4c1a76f30ce65ede55489bf77f90962d5b6c3a57f9638d433d12e00f68138",
            "type": "release",
            "version": "1.7.8"
        },
        {
            "releaseTime": "2014-04-09T07:52:16+00:00",
            "requires": {
                "org.lwjgl": "2.*"
            },
            "sha256": "90585c3c1f09db11a062b4824330bfd0c12c21413a04445a6d9324d52c6fefea",
            "type": "release",
            "version": "1.7.7"
        },
        {
            "releaseTime": "2014-04-09T07:52:06+00:00",
            "requires": {
                "org.lwjgl": "2.*"
            },
            "sha256": "7a520dca7183bbe76532c6e3899e547fb41f40847f4b8dca6ac03929ad444279",
            "type": "release",
            "version": "1.7.6"
        },
        {
            "releaseTime": "2014-02-26T09:22:17+00:00",
            "requires": {
                "org.lwjgl": "2.*"
            },
            "sha256": "f8d869e832a40ef07946d3c77374e42a462a1a6344015a2c6274de30f23749d0",
            "type": "release",
            "version": "1.7.5"
        },
        {
            "releaseTime": "2013-12-09T12:28:10+00:00",
            "requires": {
                "org.lwjgl": "2.*"
            },
            "sha256": "982d8b291fa3702fc31ebdc21e2c755763ab904e15e4a3bd77f41246d497c6ee",
            "type": "release",
            "version": "1.7.4"
        },
        {
            "releaseTime": "2013-12-06T13:55:34+00:00",
            "requires": {
                "org.lwjgl": "2.*"
            },
            "sha256": "1ce17948a855627890d8d50b6ca177af49fe2821d58d60ac4a433af81579b5b8",
            "type": "release",
            "version": "1.7.3"
        },
        {
            "releaseTime": "2013-10-25T13:00:00+00:00",
            "requires": {
                "org.lwjgl": "2.*"
            },
            "sha256": "440017822b0ef8fb9337c6f5cfcff333e6d16de2ab3645323f4d851bba2a4e9b",
            "type": "release",
            "version": "1.7.2"
        },
        {
            "releaseTime": "2013-09-19T15:52:37+00:00",
            "requires": {
                "org.lwjgl": "2.*"
            },
            "sha256": "8b4da43f03c761a410633daae1931d5c99c66bc656f7eb16b276eb194c564376",
            "type": "release",
            "version": "1.6.4"
        },
        {
            "releaseTime": "2013-07-05T13:09:02+00:00",
            "requires": {
                "org.lwjgl": "2.*"
            },
            "sha256": "446690a2988e19ad309719e184ef0e2e059bf2214da9d40414eed34a7d656ae8",
            "type": "release",
            "version": "1.6.2"
        },
        {
            "releaseTime": "2013-06-28T14:48:41+00:00",
            "requires": {
                "org.lwjgl": "2.*"
            },
            "sha256": "c302081b87803c0c9448b95bde9dd919f43a7a4f4e6e7bd7b15506a735cc3a7b",
            "type": "release",
            "version": "1.6.1"
        },
        {
            "releaseTime": "2013-04-25T17:45:00+02:00",
            "requires": {
                "org.lwjgl": "2.*"
            },
            "sha256": "f1478d180d1afa25056b26587066fa9c2b74f3ae61805ed651ee5ccb316c47c2",
            "type": "release",
            "version": "1.5.2"
        },
        {
            "releaseTime": "2013-03-20T12:00:00+02:00",
            "requires": {
                "org.lwjgl": "2.*"
            },
            "sha256": "476da4b057ee7f6f76edb74af82133e8db8648c3687c24cbf03f4a13574a90e5",
            "type": "release",
            "version": "1.5.1"
        },
        {
            "releaseTime": "2012-12-28T00:00:00+02:00",
            "requires": {
                "org.lwjgl": "2.*"
            },
            "sha256": "e8854baaf36770f8f07affb82acca35efb1a4f463ae5562f35cae00925016d35",
            "type": "release",
            "version": "1.4.7"
        },
        {
            "releaseTime": "2012-12-20T00:00:00+02:00",
            "requires": {
                "org.lwjgl": "2.*"
            },
            "sha256": "78a4e3eb5e270f8cc1d48279d67168c3fdea037776ba1537a99ddc5e8ef1033c",
            "type": "release",
            "version": "1.4.6"
        },
        {
            "releaseTime": "2012-11-20T00:00:00+02:00",
            "requires": {
                "org.lwjgl": "2.*"
            },
            "sha256": "0c2c323212ee99a59d369dc686f42daf9194eb90e5b1194b540b615a3b65b11e",
            "type": "release",
            "version": "1.4.5"
        },
        {
            "releaseTime": "2012-11-14T00:00:00+02:00",
            "requires": {
                "org.lwjgl": "2.*"
            },
            "sha256": "0617e4748683a2090400f1c5ec47138de5aa45da49219f7368c07fbd1e0ce646",
            "type": "release",
            "version": "1.4.4"
        },
        {
            "releaseTime": "2012-10-25T00:00:00+02:00",
            "requires": {
                "org.lwjgl": "2.*"
            },
            "sha256": "087053e15af0f466fdc4e4f17bb20f36a87739075daa4630da23cc27212f2ed3",
            "type": "release",
            "version": "1.4.2"
        },
        {
            "releaseTime": "2012-08-16T00:00:00+02:00",
            "requires": {
                "org.lwjgl": "2.*"
            },
            "sha256": "2c6ca23e3d667a177a7f795a1e43a9ccd5fd42561e351b796cb329cffcc2b113",
            "type": "release",
            "version": "1.3.2"
        },
        {
            "releaseTime": "2012-08-01T00:00:00+02:00",
            "requires": {
                "org.lwjgl": "2.*"
            },
            "sha256": "4c91b8468dac03a2db8e30a5aedab3ec5582d1e2d65d4984f83def137f84f0ba",
            "type": "release",
            "version": "1.3.1"
        },
        {
            "releaseTime": "2012-03-30T00:00:00+02:00",
            "requires": {
                "org.lwjgl": "2.*"
            },
            "sha256": "a1a0965c9c810f5ade4a449c6e3fbd4c7bf73c3ce9eb58b84078c873df691f4c",
            "type": "release",
            "version": "1.2.5"
        },
        {
            "releaseTime": "2012-03-22T00:00:00+02:00",
            "requires": {
                "org.lwjgl": "2.*"
            },
            "sha256": "76c12ac75c74d25766a8f5b5ab1b444df5d160c356e03b17b14e658d52b4a141",
            "type": "release",
            "version": "1.2.4"
        },
        {
            "releaseTime": "2012-03-02T00:00:00+02:00",
            "requires": {
                "org.lwjgl": "2.*"
            },
            "sha256": "75afdbb9b7cfbd0799c51bf6aa3afc64dad53fb2bf0863582f2f8441d42a33a0",
            "type": "release",
            "version": "1.2.3"
        },
        {
            "releaseTime": "2012-03-01T00:00:01+02:00",
            "requires": {
                "org.lwjgl": "2.*"
            },
            "sha256": "cd9bf53456baca24a081f9c838c014917f300dcc467b3dc3a1503f65425c3c87",
            "type": "release",
            "version": "1.2.2"
        },
        {
            "releaseTime": "2012-03-01T00:00:00+02:00",
            "requires": {
                "org.lwjgl": "2.*"
            },
            "sha256": "b8c743b8cf39300c123288edf671a92885db877d5c52fd01be246b0d8b0b7e0f",
            "type": "release",
            "version": "1.2.1"
        },
        {
            "releaseTime": "2012-01-12T00:00:00+02:00",
            "requires": {
                "org.lwjgl": "2.*"
            },
            "sha256": "fd69a89dd863b444b5f6c87e371e6878c73add2d86119da660683e26f0ae1161",
            "type": "release",
            "version": "1.1"
        },
        {
            "releaseTime": "2011-11-18T00:00:00+02:00",
            "requires": {
                "org.lwjgl": "2.*"
            },
            "sha256": "998ceca76bb8e55e12e0bacf53223238ab03bd4c92c1c2f3101e51993221c901",
            "type": "release",
            "version": "1.0"
        },
        {
            "releaseTime": "2011-09-19T00:00:00+02:00",
            "requires": {
                "org.lwjgl": "2.*"
            },
            "sha256": "30d6fd58d1b5d223eca79c529ad4b4336434860da14f50d83107e690fd408a40",
            "type": "old_beta",
            "version": "b1.8.1"
        },
        {
            "releaseTime": "2011-09-15T00:00:00+02:00",
            "requires": {
                "org.lwjgl": "2.*"
            },
            "sha256": "eb04336921deca482b7453416b36cf609e98a5f33913e3cd41f51ef28f646ac5",
            "type": "old_beta",
            "version": "b1.8"
        },
        {
            "releaseTime": "2011-07-08T00:00:00+02:00",
            "requires": {
                "org.lwjgl": "2.*"
            },
            "sha256": "ae9fd472e52018b16f3573820cdc57b266fcb7d658f39a2649d983bbe3e7b8b8",
            "type": "old_beta",
            "version": "b1.7.3"
        },
        {
            "releaseTime": "2011-07-01T00:00:00+02:00",
            "requires": {
                "org.lwjgl": "2.*"
            },
            "sha256": "04bd7b08b50717acdeac4ccc0708c8bc8191ec4647ba50b015b61a4667119600",
            "type": "old_beta",
            "version": "b1.7.2"
        },
        {
            "releaseTime": "2011-06-30T00:00:00+02:00",
            "requires": {
                "org.lwjgl": "2.*"
            },
            "sha256": "61f2f43bbedf675410b05de10da237b845f6635ca0bd9468c8889ed2493c7a63",
            "type": "old_beta",
            "version": "b1.7"
        },
        {
            "releaseTime": "2011-05-31T00:00:00+02:00",
            "requires": {
                "org.lwjgl": "2.*"
            },
            "sha256": "ec0396d119bdccfb51b4bc99690f9fa4947354c6982fd942209f5d8554dd4eac",
            "type": "old_beta",
            "version": "b1.6.6"
        },
        {
            "releaseTime": "2011-05-28T00:00:00+02:00",
            "requires": {
                "org.lwjgl": "2.*"
            },
            "sha256": "5034b6f118c1019f5d19773e9ec6a8b4bfa686fc613d7e34cb0403a331ddee45",
            "type": "old_beta",
            "version": "b1.6.5"
        },
        {
            "releaseTime": "2011-05-26T00:00:04+02:00",
            "requires": {
                "org.lwjgl": "2.*"
            },
            "sha256": "7ab0362b21e67574132286054a2b893f307d73896f57d6fb2edbb7a2a135db73",
            "type": "old_beta",
            "version": "b1.6.4"
        },
        {
            "releaseTime": "2011-05-26T00:00:03+02:00",
            "requires": {
                "org.lwjgl": "2.*"
            },
            "sha256": "35ce3ca119a78cc2c6396b93492c75bb5fa2d4294dc7e88a576c461b3f7b31ce",
            "type": "old_beta",
            "version": "b1.6.3"
        },
        {
            "releaseTime": "2011-05-26T00:00:02+02:00",
            "requires": {
                "org.lwjgl": "2.*"
            },
            "sha256": "715b6827e6b4b8daad489d05a80947fcd65b7320c497d4bcfa1928d162ee221e",
            "type": "old_beta",
            "version": "b1.6.2"
        },
        {
            "releaseTime": "2011-05-26T00:00:01+02:00",
            "requires": {
                "org.lwjgl": "2.*"
            },
            "sha256": "004c6eff699de1b53fadc1417d3da4165b4a8f3b8c92cdcfccf7fa7fa36bfa73",
            "type": "old_beta",
            "version": "b1.6.1"
        },
        {
            "releaseTime": "2011-05-26T00:00:00+02:00",
            "requires": {
                "org.lwjgl": "2.*"
            },
            "sha256": "34853a0f182d67479074873fc4247f2c7dd4a55d80809929dafb2e764d2bb747",
            "type": "old_beta",
            "version": "b1.6"
        },
        {
            "releaseTime": "2011-04-20T00:00:00+02:00",
            "requires": {
                "org.lwjgl": "2.*"
            },
            "sha256": "20961a271a5e6c5700596ab5ed7e4fa1e8e0689d028ee0b474d7e59ca06317bb",
            "type": "old_beta",
            "version": "b1.5_01"
        },
        {
            "releaseTime": "2011-04-19T00:00:00+02:00",
            "requires": {
                "org.lwjgl": "2.*"
            },
            "sha256": "4f6e6806a23bc031ba4b88f2f3989b9ecbcb5f5887be70b8bf3b071996f7251f",
            "type": "old_beta",
            "version": "b1.5"
        },
        {
            "releaseTime": "2011-04-05T00:00:00+02:00",
            "requires": {
                "org.lwjgl": "2.*"
            },
            "sha256": "bccbee5b86475d24188bf26edfeddff4439d3fdd26976efc81973b28a0a83c97",
            "type": "old_beta",
            "version": "b1.4_01"
        },
        {
            "releaseTime": "2011-03-31T00:00:00+02:00",
            "requires": {
                "org.lwjgl": "2.*"
            },
            "sha256": "dca19ece56a0626599a57efead32ca922a1b6d2808dd00bea2069eda24413df3",
            "type": "old_beta",
            "version": "b1.4"
        },
        {
            "releaseTime": "2011-02-23T00:00:00+02:00",
            "requires": {
                "org.lwjgl": "2.*"
            },
            "sha256": "9730f91df970465646462df8ac8367cbef5972bed464320cc0ef63399237f968",
            "type": "old_beta",
            "version": "b1.3_01"
        },
        {
            "releaseTime": "2011-02-22T00:00:00+02:00",
            "requires": {
                "org.lwjgl": "2.*"
            },
            "sha256": "d83d58308e1e609e62cf5a64bfa8b842feab47b67468b7a974570572c89ac6db",
            "type": "old_beta",
            "version": "b1.3b"
        },
        {
            "releaseTime": "2011-01-21T00:00:00+02:00",
            "requires": {
                "org.lwjgl": "2.*"
            },
            "sha256": "98e5c9f324b6a189df2f4f2d93adac666693d02718936508aab4d98d32deef92",
            "type": "old_beta",
            "version": "b1.2_02"
        },
        {
            "releaseTime": "2011-01-14T00:00:00+02:00",
            "requires": {
                "org.lwjgl": "2.*"
            },
            "sha256": "cd3d4dffab82f7ed807145e5802f06968653602e7d9f09ff6821a4b1cedde65c",
            "type": "old_beta",
            "version": "b1.2_01"
        },
        {
            "releaseTime": "2011-01-13T00:00:00+02:00",
            "requires": {
                "org.lwjgl": "2.*"
            },
            "sha256": "463497c95be991ac1ffdf4d5096188495728d72223801f3c740252a1b9174716",
            "type": "old_beta",
            "version": "b1.2"
        },
        {
            "releaseTime": "2010-12-22T00:00:01+02:00",
            "requires": {
                "org.lwjgl": "2.*"
            },
            "sha256": "fb4c17f08b6e0143fb6342ab36622e92a9b8b06c5198447c19dcfa26e90d9126",
            "type": "old_beta",
            "version": "b1.1_02"
        },
        {
            "releaseTime": "2010-12-22T00:00:00+02:00",
            "requires": {
                "org.lwjgl": "2.*"
            },
            "sha256": "d7c141fbd7404c2e3aa814a3534e47de9bc8b49d65b1ec9077c414fcdaaa8148",
            "type": "old_beta",
            "version": "b1.1_01"
        },
        {
            "releaseTime": "2010-12-21T00:00:00+02:00",
            "requires": {
                "org.lwjgl": "2.*"
            },
            "sha256": "35c36d12d16782d49fb836254ce2bd9e2955603bba8f66b8245ec085583b756a",
            "type": "old_beta",
            "version": "b1.0.2"
        },
        {
            "releaseTime": "2010-12-20T00:00:01+02:00",
            "requires": {
                "org.lwjgl": "2.*"
            },
            "sha256": "cd22c3cb0e08f8edce3edcf15b85ea4f4e28fb8d41dd78c7f1d04b036cc71a3c",
            "type": "old_beta",
            "version": "b1.0_01"
        },
        {
            "releaseTime": "2010-12-20T00:00:00+02:00",
            "requires": {
                "org.lwjgl": "2.*"
            },
            "sha256": "44be23398cdced14bba83321510a5e9f3367f531b6808426f916596d6678ce3a",
            "type": "old_beta",
            "version": "b1.0"
        },
        {
            "releaseTime": "2010-12-03T00:00:00+02:00",
            "requires": {
                "org.lwjgl": "2.*"
            },
            "sha256": "2bef33beb1a4e1b2b3d37adb1d2146f76a90d2b8e9b0dc73ddf673e571638481",
            "type": "old_alpha",
            "version": "a1.2.6"
        },
        {
            "releaseTime": "2010-12-01T00:00:00+02:00",
            "requires": {
                "org.lwjgl": "2.*"
            },
            "sha256": "384478551332cd2592fc293efdb905885a8357a46cbe47e4d85237c7e794b355",
            "type": "old_alpha",
            "version": "a1.2.5"
        },
        {
            "releaseTime": "2010-11-30T00:00:00+02:00",
            "requires": {
                "org.lwjgl": "2.*"
            },
            "sha256": "b9a87d5429d4abfd88bebd1139df62b13cbfe0b10c93c082f4db44dfcfd14399",
            "type": "old_alpha",
            "version": "a1.2.4_01"
        },
        {
            "releaseTime": "2010-11-26T00:00:00+02:00",
            "requires": {
                "org.lwjgl": "2.*"
            },
            "sha256": "30144efb9555b31d4b0fb18accb79e4458f3a02ec438e97b712282646d749ee6",
            "type": "old_alpha",
            "version": "a1.2.3_04"
        },
        {
            "releaseTime": "2010-11-25T00:00:00+02:00",
            "requires": {
                "org.lwjgl": "2.*"
            },
            "sha256": "7b147f51e0922b1d8780c7f19b498091db1fa2233b638db595b18cebdd0a2235",
            "type": "old_alpha",
            "version": "a1.2.3_02"
        },
        {
            "releaseTime": "2010-11-24T00:00:01+02:00",
            "requires": {
                "org.lwjgl": "2.*"
            },
            "sha256": "caa350b0bb2ee27bf6ab6d841a5e400f26163d77e019f06553e4b201eb68e52d",
            "type": "old_alpha",
            "version": "a1.2.3_01"
        },
        {
            "releaseTime": "2010-11-24T00:00:00+02:00",
            "requires": {
                "org.lwjgl": "2.*"
            },
            "sha256": "63dc13ba49b308563bc12232c75d0c023ab684646469fc71f6e34f3b14324da0",
            "type": "old_alpha",
            "version": "a1.2.3"
        },
        {
            "releaseTime": "2010-11-10T00:00:01+02:00",
            "requires": {
                "org.lwjgl": "2.*"
            },
            "sha256": "2a7aa59d16efcbd8cec587d96473505c565d95f3c0bb7fd4fe0b37e3b348fff5",
            "type": "old_alpha",
            "version": "a1.2.2b"
        },
        {
            "releaseTime": "2010-11-10T00:00:00+02:00",
            "requires": {
                "org.lwjgl": "2.*"
            },
            "sha256": "43a169d7d284d7a18ab898211a500732a0553cb1999dab122a3550cfd142f8aa",
            "type": "old_alpha",
            "version": "a1.2.2a"
        },
        {
            "releaseTime": "2010-11-05T00:00:01+02:00",
            "requires": {
                "org.lwjgl": "2.*"
            },
            "sha256": "7b6e1016a78acdc243babf56914bfec29c508c4653dbfb4e3a353d75178e9102",
            "type": "old_alpha",
            "version": "a1.2.1_01"
        },
        {
            "releaseTime": "2010-11-05T00:00:00+02:00",
            "requires": {
                "org.lwjgl": "2.*"
            },
            "sha256": "eebf3c1bbc1c00a54e3aa81153d10dbb620f4d77a0f8b93c7b6420081e6231d8",
            "type": "old_alpha",
            "version": "a1.2.1"
        },
        {
            "releaseTime": "2010-11-04T00:00:00+02:00",
            "requires": {
                "org.lwjgl": "2.*"
            },
            "sha256": "8beacee9b461f3b8fd5e77524839a5a105e477cbaa112c329f22d5c0068ce284",
            "type": "old_alpha",
            "version": "a1.2.0_02"
        },
        {
            "releaseTime": "2010-10-31T00:00:00+02:00",
            "requires": {
                "org.lwjgl": "2.*"
            },
            "sha256": "b3911f1294f37f887039abc88df95ffef32cc5dfac1c18c9052ed7cf20b3dfc2",
            "type": "old_alpha",
            "version": "a1.2.0_01"
        },
        {
            "releaseTime": "2010-10-30T00:00:00+02:00",
            "requires": {
                "org.lwjgl": "2.*"
            },
            "sha256": "8eec7ecb481b6786050bdcc84bf0aa47ed5b7cff4ec11c48c520d9e49eb42e5d",
            "type": "old_alpha",
            "version": "a1.2.0"
        },
        {
            "releaseTime": "2010-09-23T00:00:00+02:00",
            "requires": {
                "org.lwjgl": "2.*"
            },
            "sha256": "1326cc63486f12a0ac270fd49b1c590d55c92fef328d3f12cd369dc47d596e73",
            "type": "old_alpha",
            "version": "a1.1.2_01"
        },
        {
            "releaseTime": "2010-09-20T00:00:00+02:00",
            "requires": {
                "org.lwjgl": "2.*"
            },
            "sha256": "f26374ffb35e6c0135767f710696863d5076264aaff27714a0523ee807476d1f",
            "type": "old_alpha",
            "version": "a1.1.2"
        },
        {
            "releaseTime": "2010-09-13T00:00:00+02:00",
            "requires": {
                "org.lwjgl": "2.*"
            },
            "sha256": "1676a023735ddd9c69c7aed492ece9e80c141b969168f9c6b4cc947a757d3cfe",
            "type": "old_alpha",
            "version": "a1.1.0"
        },
        {
            "releaseTime": "2010-08-23T00:00:00+02:00",
            "requires": {
                "org.lwjgl": "2.*"
            },
            "sha256": "700a92eb4581b6ea783ce2b9fc3627a6657e1d418a7895bccbc1176091c27328",
            "type": "old_alpha",
            "version": "a1.0.17_04"
        },
        {
            "releaseTime": "2010-08-20T00:00:00+02:00",
            "requires": {
                "org.lwjgl": "2.*"
            },
            "sha256": "4d6219c2e31218481b2a883302ea4bb4eee492c17da5db7535b73b38ec330301",
            "type": "old_alpha",
            "version": "a1.0.17_02"
        },
        {
            "releaseTime": "2010-08-12T00:00:00+02:00",
            "requires": {
                "org.lwjgl": "2.*"
            },
            "sha256": "3e838d0c421c44f855105f84c833fb51a99a7dd8df2df144ed54bf6e9733ab03",
            "type": "old_alpha",
            "version": "a1.0.16"
        },
        {
            "releaseTime": "2010-08-04T00:00:00+02:00",
            "requires": {
                "org.lwjgl": "2.*"
            },
            "sha256": "0314c2a44cbd247631e5d746cf281d72b63b7888e5b8e4bd742996991c12bbd5",
            "type": "old_alpha",
            "version": "a1.0.15"
        },
        {
            "releaseTime": "2010-07-30T00:00:00+02:00",
            "requires": {
                "org.lwjgl": "2.*"
            },
            "sha256": "451b40c8e3a34e73a8888755c4fbe26dbde95a05b181f029be7b49d8061f91fa",
            "type": "old_alpha",
            "version": "a1.0.14"
        },
        {
            "releaseTime": "2010-07-23T00:00:00+02:00",
            "requires": {
                "org.lwjgl": "2.*"
            },
            "sha256": "d3ecc90aebd5cefc80796c6d0f336c5699cfc69d90953709081901f932ac70f8",
            "type": "old_alpha",
            "version": "a1.0.11"
        },
        {
            "releaseTime": "2010-07-13T00:00:00+02:00",
            "requires": {
                "org.lwjgl": "2.*"
            },
            "sha256": "484c71b76ffe27be4b41abd44afa32f5d94277aae6c59bf493de11b4b1d753e9",
            "type": "old_alpha",
            "version": "a1.0.5_01"
        },
        {
            "releaseTime": "2010-07-09T00:00:00+02:00",
            "requires": {
                "org.lwjgl": "2.*"
            },
            "sha256": "7cd6986623e8e5cb4c96786f1c14e18ff5f8b40b3ce5e411d1d1d9e3c676f263",
            "type": "old_alpha",
            "version": "a1.0.4"
        },
        {
            "releaseTime": "2010-06-16T00:00:00+02:00",
            "requires": {
                "org.lwjgl": "2.*"
            },
            "sha256": "b5e5d495c9ecb716b391d1a87f586ee27aed33a3630a1ccaf0ba3b20043ec193",
            "type": "old_alpha",
            "version": "inf-20100618"
        },
        {
            "releaseTime": "2009-12-22T00:00:00+02:00",
            "requires": {
                "org.lwjgl": "2.*"
            },
            "sha256": "9b147c990b8a1df9767fd04ae44fd35a8d74846bab90abbdf102a86d3dba9874",
            "type": "old_alpha",
            "version": "c0.30_01c"
        },
        {
            "releaseTime": "2009-05-31T00:00:00+02:00",
            "requires": {
                "org.lwjgl": "2.*"
            },
            "sha256": "8dd07094e9fba5883a33467d6c071fd91bde95d9e7083fbf254905e6b9a46d5f",
            "type": "old_alpha",
            "version": "c0.0.13a"
        },
        {
            "releaseTime": "2009-05-22T00:00:00+02:00",
            "requires": {
                "org.lwjgl": "2.*"
            },
            "sha256": "e545ee5bcff457312d1b7b70c83ca3dec0957bcef610065365a51b3afaddf52c",
            "type": "old_alpha",
            "version": "c0.0.13a_03"
        },
        {
            "releaseTime": "2009-05-17T00:00:00+02:00",
            "requires": {
                "org.lwjgl": "2.*"
            },
            "sha256": "ac3b9a06d946cbdd853c6652b67162cbd166a569e482d62332d8ada9d4a7f43c",
            "type": "old_alpha",
            "version": "c0.0.11a"
        },
        {
            "releaseTime": "2009-05-16T13:48:00+02:00",
            "requires": {
                "org.lwjgl": "2.*"
            },
            "sha256": "a57787a4a0e1128233bf7fb87e60101d32349dee7994de517e153afcffef3abd",
            "type": "old_alpha",
            "version": "rd-161348"
        },
        {
            "releaseTime": "2009-05-16T00:52:00+02:00",
            "requires": {
                "org.lwjgl": "2.*"
            },
            "sha256": "9e3e03c0a0ebfd5ae97be9b5d88105e518519f23f19ef6ae5936031e3e1e649a",
            "type": "old_alpha",
            "version": "rd-160052"
        },
        {
            "releaseTime": "2009-05-14T22:00:00+00:00",
            "requires": {
                "org.lwjgl": "2.*"
            },
            "sha256": "507364b41a4f47bf66dc4442cc22e30df7027e980272d6428295c04b9df43446",
            "type": "old_alpha",
            "version": "rd-20090515"
        },
        {
            "releaseTime": "2009-05-13T23:28:00+02:00",
            "requires": {
                "org.lwjgl": "2.*"
            },
            "sha256": "20b2fc722b6f326770deb07bfa3da0c4cc0262dbd34f1abbbc44fd4bfce83d24",
            "type": "old_alpha",
            "version": "rd-132328"
        },
        {
            "releaseTime": "2009-05-13T22:11:00+02:00",
            "requires": {
                "org.lwjgl": "2.*"
            },
            "sha256": "d5665296d59f054e0209aa156985267f7e68bd3e59efb86b67fddb6a5c6ad70f",
            "type": "old_alpha",
            "version": "rd-132211"
        }
    ]
}