{
    "+traits": [
        "legacyFML"
    ],
    "formatVersion": 1,
    "jarMods": [
        {
            "downloads": {
                "artifact": {
                    "sha1": "038de0718c800c605deda3cc1ea63f1467cc0d85",
                    "size": 790109,
                    "url": "https://files.minecraftforge.net/maven/net/minecraftforge/forge/1.3.2-4.1.4.290/forge-1.3.2-4.1.4.290-universal.zip"
                }
            },
            "name": "net.minecraftforge:forge:1.3.2-4.1.4.290:universal"
        }
    ],
    "name": "Forge",
    "order": 5,
    "releaseTime": "2012-09-26T22:23:24+00:00",
    "requires": [
        {
            "equals": "1.3.2",
            "uid": "net.minecraft"
        }
    ],
    "uid": "net.minecraftforge",
    "version": "4.1.4.290"
}