{
    "formatVersion": 1,
    "jarMods": [
        {
            "downloads": {
                "artifact": {
                    "sha1": "1902fd2cee020fb0cc37323df70123c9f1ef521f",
                    "size": 835994,
                    "url": "https://files.minecraftforge.net/maven/net/minecraftforge/forge/1.2.5-3.3.8.159/forge-1.2.5-3.3.8.159-client.zip"
                }
            },
            "name": "net.minecraftforge:forge:1.2.5-3.3.8.159:client"
        }
    ],
    "name": "Forge",
    "order": 5,
    "releaseTime": "2012-07-02T20:30:34+00:00",
    "requires": [
        {
            "equals": "1.2.5",
            "uid": "net.minecraft"
        }
    ],
    "uid": "net.minecraftforge",
    "version": "3.3.8.159"
}