{
    "+traits": [
        "legacyFML"
    ],
    "formatVersion": 1,
    "jarMods": [
        {
            "downloads": {
                "artifact": {
                    "sha1": "a6769078d9dbeda08be78d1ff98e8398948db030",
                    "size": 1726503,
                    "url": "https://files.minecraftforge.net/maven/net/minecraftforge/forge/1.4.6-6.5.0.455/forge-1.4.6-6.5.0.455-universal.zip"
                }
            },
            "name": "net.minecraftforge:forge:1.4.6-6.5.0.455:universal"
        }
    ],
    "name": "Forge",
    "order": 5,
    "releaseTime": "2012-12-18T09:05:42+00:00",
    "requires": [
        {
            "equals": "1.4.6",
            "uid": "net.minecraft"
        }
    ],
    "uid": "net.minecraftforge",
    "version": "6.5.0.455"
}