{
    "formatVersion": 1,
    "name": "Java Runtimes",
    "uid": "net.minecraft.java",
    "versions": [
        {
            "recommended": false,
            "releaseTime": "2025-05-19T08:30:12+00:00",
            "sha256": "11219b2cbe95fdad53df99f159360d9de71f8a130b38aafb7c77c90fefc39d72",
            "version": "java21"
        },
        {
            "recommended": false,
            "releaseTime": "2021-11-15T14:19:45+00:00",
            "sha256": "e1bd45f8f37ee3c5b889e1f82879bde1547dc2e59c3567baf13b6d933d920fb4",
            "version": "java17"
        },
        {
            "recommended": false,
            "releaseTime": "2021-05-10T16:43:02+00:00",
            "sha256": "bbfc67adc6d90a68d383fd324c1b189950c5ea6f8479714552be773a1c79ebc0",
            "version": "java16"
        },
        {
            "recommended": false,
            "releaseTime": "2020-11-17T19:26:25+00:00",
            "sha256": "f7f3b34ad151c54519a586515ce8f0c567b2436855cd442432a3fe412d6bfa32",
            "version": "java8"
        }
    ]
}