{
    "formatVersion": 1,
    "libraries": [
        {
            "name": "net.fabricmc:intermediary:23w51a",
            "url": "https://maven.fabricmc.net"
        }
    ],
    "name": "Intermediary Mappings",
    "order": 11,
    "releaseTime": "2023-12-18T15:14:15+00:00",
    "requires": [
        {
            "equals": "23w51a",
            "uid": "net.minecraft"
        }
    ],
    "type": "release",
    "uid": "net.fabricmc.intermediary",
    "version": "23w51a",
    "volatile": true
}